{
  "type": "FeatureCollection",
  "features": [
    {
      "type": "Feature",
      "properties": {
        "名称": "奇遇花园",
        "下载速度": "22 Mbps",
        "Speedtest 链接": "http://www.speedtest.net/my-result/4629928302",
        "参考价格": "30-40 元",
        "评论 (@xhacker)": "有电源，网速快，环境不错，咖啡也不错。",
        "marker-color": "#50C240",
        "marker-symbol": "cafe"
      },
      "geometry": {
        "type": "Point",
        "coordinates": [
          116.342,
          39.941
        ]
      }
    },
    {
      "type": "Feature",
      "properties": {
        "名称": "May Café",
        "营业状态": "停业",
        "下载速度": "41 Mbps",
        "Speedtest 链接": "http://www.speedtest.net/my-result/4850194225",
        "参考价格": "25-40 元",
        "评论 (@mckelvin)": "有电源，网速快，环境不错，人不多。",
        "marker-color": "#BEBEBE",
        "marker-symbol": "cafe"
      },
      "geometry": {
        "type": "Point",
        "coordinates": [
          116.328977,
          40.03278
        ]
      }
    }
  ]
}
